pycellslib/__init__.py
pycellslib/cells.py
pycellslib/onedimensional/__init__.py
pycellslib/onedimensional/neighborhoods.py
pycellslib/onedimensional/rules.py
pycellslib/onedimensional/topologies.py
pycellslib/twodimensional/neighborhoods.py
pycellslib/twodimensional/rules.py
pycellslib/twodimensional/topologies.py
pycellslib/visualizers/__init__.py
pycellslib/visualizers/curses_visualizer.py
pycellslib/visualizers/matplotlib_visualizer.py
pycellslib/visualizers/pygame_visualizer.py
pycellslib-0.1.0.dist-info/LICENSE
pycellslib-0.1.0.dist-info/WHEEL
pycellslib-0.1.0.dist-info/METADATA
pycellslib-0.1.0.dist-info/RECORD
