Metadata-Version: 2.1
Name: pycellslib
Version: 0.1.0
Summary: Library for simulation and visualization of any cellular automata
Author: Luis Papiernik
Author-email: lpapiernik24@gmail.com
Requires-Python: >=3.8,<3.12
Classifier: Programming Language :: Python :: 3
Classifier: Programming Language :: Python :: 3.10
Classifier: Programming Language :: Python :: 3.8
Classifier: Programming Language :: Python :: 3.9
Requires-Dist: matplotlib (>=3.5.2,<4.0.0)
Requires-Dist: numpy (>=1.23.1,<2.0.0)
Requires-Dist: pygame (>=2.1.2,<3.0.0)
Requires-Dist: scipy (>=1.8,<2.0)
